nb_prep/__init__.py
nb_prep/_utils.py
nb_prep/cli.py
nb_prep/files.py
nb_prep/nb_convert_strip.py
tests/__init__.py
tests/test_cli.py
tests/test_convert_notebook.py
tests/test_files.py
tests/test_insert_commithash_filename_placeholder.py
tests/test_precommit.py
nb_prep-1.0.2.dist-info/LICENSE
nb_prep-1.0.2.dist-info/METADATA
nb_prep-1.0.2.dist-info/WHEEL
nb_prep-1.0.2.dist-info/entry_points.txt
nb_prep-1.0.2.dist-info/top_level.txt
nb_prep-1.0.2.dist-info/RECORD
