Metadata-Version: 2.1
Name: nb-prep
Version: 1.0.2
Summary: Prepares jupyter notebooks for storing stripped versions in git and sharing results with stakeholders
Home-page: https://github.com/allianz-direct/nb_prep
Author: Tim Vink
Author-email: tim.vink@allianzdirect.nl
License: MIT
Keywords: precommit nbconvert nbstripout jupyter notebook python
Platform: UNKNOWN
Classifier: Programming Language :: Python :: 3
Classifier: Programming Language :: Python :: 3.7
Classifier: Programming Language :: Python :: 3.8
Classifier: Programming Language :: Python :: 3.9
Classifier: Programming Language :: Python :: 3.10
Classifier: License :: OSI Approved :: MIT License
Classifier: Operating System :: OS Independent
Requires-Python: >=3.7
License-File: LICENSE
Requires-Dist: jupyter-client (>=7.1.1)
Requires-Dist: nbconvert (>=6.4.0)
Requires-Dist: pre-commit (>=2.16.0)
Requires-Dist: typer (>=0.4.0)
Requires-Dist: nbstripout (>=0.5.0)
